{"date":"2026-03-12","stocks":{"ABCAPITAL":{"eq_volume":3039653,"eq_turnover":973437836.4,"eq_high":325,"eq_low":316.4,"eq_close":319.95,"fut_volume":2406,"fut_oi":46388400,"fut_oi_change":-548700,"fut_turnover":2398322130,"opt_volume":7446,"opt_oi":25327000,"opt_turnover":7758340860,"ce_volume":4914,"pe_volume":2532},"ADANIENSOL":{"eq_volume":1132800,"eq_turnover":1134557182.4,"eq_high":1019,"eq_low":976,"eq_close":1004.4,"fut_volume":2500,"fut_oi":18610425,"fut_oi_change":-176850,"fut_turnover":1693069357.5,"opt_volume":9605,"opt_oi":5460750,"opt_turnover":6826734877.5,"ce_volume":7635,"pe_volume":1970},"INDHOTEL":{"eq_volume":4723816,"eq_turnover":2925417761.9,"eq_high":631.9,"eq_low":603.75,"eq_close":624.95,"fut_volume":5188,"fut_oi":19811000,"fut_oi_change":-871000,"fut_turnover":3212342850,"opt_volume":13965,"opt_oi":15519000,"opt_turnover":8832537750,"ce_volume":6472,"pe_volume":7493},"INDIANB":{"eq_volume":1025100,"eq_turnover":930726956.1,"eq_high":922.3,"eq_low":890,"eq_close":909.6,"fut_volume":2453,"fut_oi":8104000,"fut_oi_change":175000,"fut_turnover":2228993600,"opt_volume":6773,"opt_oi":9317000,"opt_turnover":6403960100,"ce_volume":4259,"pe_volume":2514},"INOXWIND":{"eq_volume":20354774,"eq_turnover":1716227206.76,"eq_high":86.95,"eq_low":80.55,"eq_close":83.68,"fut_volume":4816,"fut_oi":96467800,"fut_oi_change":-518375,"fut_turnover":1457038726,"opt_volume":18432,"opt_oi":62358725,"opt_turnover":6082692187,"ce_volume":15123,"pe_volume":3309},"JINDALSTEL":{"eq_volume":1959835,"eq_turnover":2365990801.9,"eq_high":1232.1,"eq_low":1162.2,"eq_close":1225,"fut_volume":4647,"fut_oi":10012500,"fut_oi_change":-185625,"fut_turnover":3510740312.5,"opt_volume":18375,"opt_oi":6943125,"opt_turnover":14154530500,"ce_volume":11425,"pe_volume":6950},"MPHASIS":{"eq_volume":423505,"eq_turnover":926125512.2,"eq_high":2213,"eq_low":2157,"eq_close":2185.2,"fut_volume":1956,"fut_oi":5348475,"fut_oi_change":-5225,"fut_turnover":1180127437.5,"opt_volume":6994,"opt_oi":2251425,"opt_turnover":4396549052.5,"ce_volume":4512,"pe_volume":2482},"NESTLEIND":{"eq_volume":1358564,"eq_turnover":1657797127.2,"eq_high":1229.9,"eq_low":1209.3,"eq_close":1220.8,"fut_volume":2934,"fut_oi":15740000,"fut_oi_change":-127000,"fut_turnover":1792925450,"opt_volume":5965,"opt_oi":5436500,"opt_turnover":3725381225,"ce_volume":3340,"pe_volume":2625},"NTPC":{"eq_volume":23847146,"eq_turnover":9250982430.3,"eq_high":392.4,"eq_low":375.65,"eq_close":390.55,"fut_volume":17752,"fut_oi":104949000,"fut_oi_change":6142500,"fut_turnover":10325944725,"opt_volume":210586,"opt_oi":120795000,"opt_turnover":125495883525,"ce_volume":170219,"pe_volume":40367},"PRESTIGE":{"eq_volume":483947,"eq_turnover":608958314,"eq_high":1283.8,"eq_low":1237.4,"eq_close":1252.7,"fut_volume":2134,"fut_oi":5672700,"fut_oi_change":-44550,"fut_turnover":1212306840,"opt_volume":4497,"opt_oi":2525400,"opt_turnover":2719343227.5,"ce_volume":2234,"pe_volume":2263},"RBLBANK":{"eq_volume":3157302,"eq_turnover":942517443.15,"eq_high":303.15,"eq_low":292.9,"eq_close":299.8,"fut_volume":3750,"fut_oi":61125100,"fut_oi_change":755650,"fut_turnover":3555101475,"opt_volume":11723,"opt_oi":55991125,"opt_turnover":11516577328.75,"ce_volume":7027,"pe_volume":4696},"SHREECEM":{"eq_volume":40125,"eq_turnover":943185045,"eq_high":23740,"eq_low":23315,"eq_close":23500,"fut_volume":1972,"fut_oi":357300,"fut_oi_change":-3725,"fut_turnover":1159859250,"opt_volume":1982,"opt_oi":155675,"opt_turnover":1220468658.75,"ce_volume":1122,"pe_volume":860},"TATASTEEL":{"eq_volume":24413736,"eq_turnover":4698943177.82,"eq_high":194.66,"eq_low":190.1,"eq_close":193.47,"fut_volume":5925,"fut_oi":196856000,"fut_oi_change":-2464000,"fut_turnover":6287414980,"opt_volume":25661,"opt_oi":220011000,"opt_turnover":28435074910,"ce_volume":16507,"pe_volume":9154},"TCS":{"eq_volume":2752075,"eq_turnover":6745252596.1,"eq_high":2472.9,"eq_low":2436,"eq_close":2442.4,"fut_volume":15739,"fut_oi":26867575,"fut_oi_change":190050,"fut_turnover":6772283560,"opt_volume":116863,"opt_oi":27652800,"opt_turnover":52636583877.5,"ce_volume":75255,"pe_volume":41608},"TATAELXSI":{"eq_volume":227665,"eq_turnover":984409689.6,"eq_high":4380,"eq_low":4253,"eq_close":4330,"fut_volume":2704,"fut_oi":1638100,"fut_oi_change":19600,"fut_turnover":1164292240,"opt_volume":22643,"opt_oi":2690200,"opt_turnover":11338417535,"ce_volume":17346,"pe_volume":5297},"AMBUJACEM":{"eq_volume":5554429,"eq_turnover":2503948864.15,"eq_high":455.55,"eq_low":445,"eq_close":446.45,"fut_volume":5766,"fut_oi":49520100,"fut_oi_change":577500,"fut_turnover":2737977637.5,"opt_volume":9431,"opt_oi":27512100,"opt_turnover":4731339322.5,"ce_volume":6451,"pe_volume":2980},"APLAPOLLO":{"eq_volume":1360299,"eq_turnover":2705958398.2,"eq_high":2025,"eq_low":1937.2,"eq_close":2009.2,"fut_volume":3396,"fut_oi":4790800,"fut_oi_change":64050,"fut_turnover":2361411710,"opt_volume":13163,"opt_oi":3097150,"opt_turnover":9695402080,"ce_volume":7958,"pe_volume":5205},"AUROPHARMA":{"eq_volume":2110239,"eq_turnover":2760761025.6,"eq_high":1319.8,"eq_low":1289.4,"eq_close":1311.9,"fut_volume":6515,"fut_oi":21852600,"fut_oi_change":-485100,"fut_turnover":4683324690,"opt_volume":36522,"opt_oi":11169950,"opt_turnover":26557146467.5,"ce_volume":19918,"pe_volume":16604},"BAJAJHLDNG":{"eq_volume":83281,"eq_turnover":827706795,"eq_high":10103,"eq_low":9760,"eq_close":9789,"fut_volume":858,"fut_oi":221450,"fut_oi_change":3650,"fut_turnover":426102600,"opt_volume":3703,"opt_oi":210600,"opt_turnover":1947745442.5,"ce_volume":2206,"pe_volume":1497},"CDSL":{"eq_volume":1620635,"eq_turnover":1953010835.9,"eq_high":1218.5,"eq_low":1193.1,"eq_close":1210.8,"fut_volume":3367,"fut_oi":10213450,"fut_oi_change":376675,"fut_turnover":1924132232.5,"opt_volume":18986,"opt_oi":11950050,"opt_turnover":11471376587.5,"ce_volume":13339,"pe_volume":5647},"CONCOR":{"eq_volume":3982340,"eq_turnover":1857189426.45,"eq_high":471.2,"eq_low":458.45,"eq_close":467.15,"fut_volume":2441,"fut_oi":27830000,"fut_oi_change":447500,"fut_turnover":1425046187.5,"opt_volume":5201,"opt_oi":18061250,"opt_turnover":3181822500,"ce_volume":3753,"pe_volume":1448},"INDIGO":{"eq_volume":1595719,"eq_turnover":6788220956.7,"eq_high":4297.5,"eq_low":4194.1,"eq_close":4251.7,"fut_volume":12328,"fut_oi":8661300,"fut_oi_change":-31500,"fut_turnover":7880475435,"opt_volume":95571,"opt_oi":12239850,"opt_turnover":63162658815,"ce_volume":44243,"pe_volume":51328},"JIOFIN":{"eq_volume":18865160,"eq_turnover":4522854974.35,"eq_high":245.4,"eq_low":234,"eq_close":242.2,"fut_volume":6476,"fut_oi":158930500,"fut_oi_change":-1945800,"fut_turnover":3653909250,"opt_volume":35036,"opt_oi":94206800,"opt_turnover":20876711802.5,"ce_volume":26397,"pe_volume":8639},"MFSL":{"eq_volume":827123,"eq_turnover":1401012483.4,"eq_high":1722,"eq_low":1677.9,"eq_close":1696.2,"fut_volume":2029,"fut_oi":9362000,"fut_oi_change":101200,"fut_turnover":1378366440,"opt_volume":3216,"opt_oi":1785600,"opt_turnover":2250596560,"ce_volume":1878,"pe_volume":1338},"NYKAA":{"eq_volume":3655162,"eq_turnover":897948069.5,"eq_high":250.1,"eq_low":243.55,"eq_close":244.95,"fut_volume":1157,"fut_oi":42881250,"fut_oi_change":-159375,"fut_turnover":890995937.5,"opt_volume":2431,"opt_oi":13225000,"opt_turnover":1978551562.5,"ce_volume":1639,"pe_volume":792},"PAGEIND":{"eq_volume":19162,"eq_turnover":592767250,"eq_high":31555,"eq_low":30730,"eq_close":30860,"fut_volume":2303,"fut_oi":229080,"fut_oi_change":2790,"fut_turnover":1072718550,"opt_volume":13611,"opt_oi":180465,"opt_turnover":6728145122.25,"ce_volume":9610,"pe_volume":4001},"PERSISTENT":{"eq_volume":584369,"eq_turnover":2735565060.5,"eq_high":4750,"eq_low":4628,"eq_close":4714.4,"fut_volume":6561,"fut_oi":4074800,"fut_oi_change":85300,"fut_turnover":3059031400,"opt_volume":24859,"opt_oi":3037200,"opt_turnover":12310359590,"ce_volume":16349,"pe_volume":8510},"PNBHOUSING":{"eq_volume":1005815,"eq_turnover":778126824.05,"eq_high":787.35,"eq_low":756.15,"eq_close":780.15,"fut_volume":2758,"fut_oi":13064350,"fut_oi_change":-178100,"fut_turnover":1386714777.5,"opt_volume":9012,"opt_oi":4964700,"opt_turnover":4689589612.5,"ce_volume":3875,"pe_volume":5137},"SBILIFE":{"eq_volume":868643,"eq_turnover":1677851628.8,"eq_high":1948.1,"eq_low":1907,"eq_close":1939.4,"fut_volume":2403,"fut_oi":8786250,"fut_oi_change":-182250,"fut_turnover":1742965875,"opt_volume":7034,"opt_oi":5578500,"opt_turnover":5251160193.75,"ce_volume":4720,"pe_volume":2314},"TITAN":{"eq_volume":1071366,"eq_turnover":4408116964.3,"eq_high":4179,"eq_low":4033.8,"eq_close":4129.6,"fut_volume":6610,"fut_oi":9561125,"fut_oi_change":-13125,"fut_turnover":4759826277.5,"opt_volume":36624,"opt_oi":4454100,"opt_turnover":27151011588.75,"ce_volume":22416,"pe_volume":14208},"TRENT":{"eq_volume":989163,"eq_turnover":3501493699.1,"eq_high":3603.1,"eq_low":3502.5,"eq_close":3533.6,"fut_volume":6720,"fut_oi":5904700,"fut_oi_change":3600,"fut_turnover":2380092070,"opt_volume":55508,"opt_oi":4792500,"opt_turnover":20807477655,"ce_volume":35157,"pe_volume":20351},"UNIONBANK":{"eq_volume":14230468,"eq_turnover":2554183156.58,"eq_high":183.4,"eq_low":175.52,"eq_close":182.1,"fut_volume":5044,"fut_oi":83650200,"fut_oi_change":4186050,"fut_turnover":4029218707.5,"opt_volume":12869,"opt_oi":63675750,"opt_turnover":10771400136,"ce_volume":9139,"pe_volume":3730},"YESBANK":{"eq_volume":87147333,"eq_turnover":1678423584.39,"eq_high":19.52,"eq_low":19.02,"eq_close":19.31,"fut_volume":3414,"fut_oi":1013860000,"fut_oi_change":3327700,"fut_turnover":2047244891,"opt_volume":13692,"opt_oi":636181600,"opt_turnover":8633476625,"ce_volume":8846,"pe_volume":4846},"BSE":{"eq_volume":2988021,"eq_turnover":8460104103.6,"eq_high":2877.9,"eq_low":2781.2,"eq_close":2850.6,"fut_volume":7284,"fut_oi":7430250,"fut_oi_change":61875,"fut_turnover":7740664312.5,"opt_volume":59040,"opt_oi":12628125,"opt_turnover":63832870012.5,"ce_volume":31115,"pe_volume":27925},"DALBHARAT":{"eq_volume":358226,"eq_turnover":674093102.1,"eq_high":1909.1,"eq_low":1825.1,"eq_close":1894.5,"fut_volume":2608,"fut_oi":2095275,"fut_oi_change":-85150,"fut_turnover":1592665717.5,"opt_volume":24978,"opt_oi":3367000,"opt_turnover":15148426491.25,"ce_volume":4891,"pe_volume":20087},"EICHERMOT":{"eq_volume":1259945,"eq_turnover":8852196194.5,"eq_high":7227.5,"eq_low":6961,"eq_close":6975.5,"fut_volume":9191,"fut_oi":3279800,"fut_oi_change":191100,"fut_turnover":6486984500,"opt_volume":66851,"opt_oi":4134000,"opt_turnover":49967639730,"ce_volume":39329,"pe_volume":27522},"KAYNES":{"eq_volume":1473221,"eq_turnover":5400403289.1,"eq_high":3786,"eq_low":3586,"eq_close":3700.3,"fut_volume":8848,"fut_oi":3697600,"fut_oi_change":77100,"fut_turnover":3261327510,"opt_volume":42902,"opt_oi":3115900,"opt_turnover":16883742445,"ce_volume":32073,"pe_volume":10829},"KEI":{"eq_volume":523034,"eq_turnover":2272794095.5,"eq_high":4425,"eq_low":4265,"eq_close":4330,"fut_volume":4442,"fut_oi":1714650,"fut_oi_change":25025,"fut_turnover":3388132650,"opt_volume":16381,"opt_oi":1747200,"opt_turnover":13169308740,"ce_volume":11077,"pe_volume":5304},"TIINDIA":{"eq_volume":201062,"eq_turnover":507775787.7,"eq_high":2566,"eq_low":2490,"eq_close":2549.7,"fut_volume":1948,"fut_oi":3021200,"fut_oi_change":-25400,"fut_turnover":987351300,"opt_volume":3566,"opt_oi":1088800,"opt_turnover":1894464920,"ce_volume":1522,"pe_volume":2044},"ABB":{"eq_volume":596298,"eq_turnover":3780336168.5,"eq_high":6429.5,"eq_low":6146,"eq_close":6409,"fut_volume":6188,"fut_oi":2040375,"fut_oi_change":24250,"fut_turnover":4885502625,"opt_volume":54637,"opt_oi":2155750,"opt_turnover":44174816800,"ce_volume":38084,"pe_volume":16553},"BDL":{"eq_volume":1295186,"eq_turnover":1736888369.9,"eq_high":1355.1,"eq_low":1325.8,"eq_close":1349.4,"fut_volume":2482,"fut_oi":4735500,"fut_oi_change":-7700,"fut_turnover":1166694830,"opt_volume":13438,"opt_oi":6669950,"opt_turnover":6598670015,"ce_volume":9575,"pe_volume":3863},"BEL":{"eq_volume":14089623,"eq_turnover":6368813725.5,"eq_high":455,"eq_low":448.5,"eq_close":453.55,"fut_volume":9789,"fut_oi":99323925,"fut_oi_change":-565725,"fut_turnover":6316011967.5,"opt_volume":61268,"opt_oi":81672450,"opt_turnover":41032719247.5,"ce_volume":39415,"pe_volume":21853},"BHEL":{"eq_volume":16227938,"eq_turnover":4309003706.35,"eq_high":270.35,"eq_low":251.85,"eq_close":267.85,"fut_volume":11950,"fut_oi":111706875,"fut_oi_change":-1496250,"fut_turnover":8309818650,"opt_volume":57680,"opt_oi":59214750,"opt_turnover":41439627993.75,"ce_volume":38194,"pe_volume":19486},"CGPOWER":{"eq_volume":3548443,"eq_turnover":2570110802.5,"eq_high":740.25,"eq_low":701.6,"eq_close":737.3,"fut_volume":5325,"fut_oi":17028050,"fut_oi_change":517650,"fut_turnover":3300528877.5,"opt_volume":25734,"opt_oi":8496600,"opt_turnover":16669067460,"ce_volume":19399,"pe_volume":6335},"GMRAIRPORT":{"eq_volume":17490118,"eq_turnover":1636027989.06,"eq_high":95.08,"eq_low":92.08,"eq_close":93.29,"fut_volume":2948,"fut_oi":137295900,"fut_oi_change":-718425,"fut_turnover":1929712288.5,"opt_volume":6275,"opt_oi":94560075,"opt_turnover":4213573366.5,"ce_volume":2997,"pe_volume":3278},"HAL":{"eq_volume":961224,"eq_turnover":3839177324.3,"eq_high":4033.2,"eq_low":3940.8,"eq_close":4013.5,"fut_volume":5901,"fut_oi":9562350,"fut_oi_change":-161850,"fut_turnover":3538083000,"opt_volume":42400,"opt_oi":9262800,"opt_turnover":27355808880,"ce_volume":32171,"pe_volume":10229},"HCLTECH":{"eq_volume":2616965,"eq_turnover":3547225863.1,"eq_high":1363.4,"eq_low":1341,"eq_close":1358.1,"fut_volume":7661,"fut_oi":27395900,"fut_oi_change":808850,"fut_turnover":3621559585,"opt_volume":31109,"opt_oi":10186050,"opt_turnover":15200846080,"ce_volume":21028,"pe_volume":10081},"JUBLFOOD":{"eq_volume":4042856,"eq_turnover":1865692801,"eq_high":470,"eq_low":452,"eq_close":461.75,"fut_volume":6705,"fut_oi":25900000,"fut_oi_change":902500,"fut_turnover":3858136312.5,"opt_volume":22940,"opt_oi":16046250,"opt_turnover":13706640875,"ce_volume":10032,"pe_volume":12908},"OBEROIRLTY":{"eq_volume":480014,"eq_turnover":707540790.3,"eq_high":1490.4,"eq_low":1452.8,"eq_close":1470.3,"fut_volume":2975,"fut_oi":6931050,"fut_oi_change":48300,"fut_turnover":1524762295,"opt_volume":3380,"opt_oi":2609600,"opt_turnover":1803423020,"ce_volume":2043,"pe_volume":1337},"ONGC":{"eq_volume":20059801,"eq_turnover":5428508360.2,"eq_high":273,"eq_low":267.75,"eq_close":270.55,"fut_volume":8626,"fut_oi":121243500,"fut_oi_change":-423000,"fut_turnover":5272402837.5,"opt_volume":40097,"opt_oi":132828750,"opt_turnover":25488556425,"ce_volume":29947,"pe_volume":10150},"PNB":{"eq_volume":13515926,"eq_turnover":1571777543.69,"eq_high":118.13,"eq_low":113.66,"eq_close":116.61,"fut_volume":5117,"fut_oi":243064000,"fut_oi_change":-1416000,"fut_turnover":4765502080,"opt_volume":15571,"opt_oi":211600000,"opt_turnover":15168802480,"ce_volume":9598,"pe_volume":5973},"POWERGRID":{"eq_volume":15284297,"eq_turnover":4624118263.8,"eq_high":304.9,"eq_low":295.1,"eq_close":303.6,"fut_volume":8421,"fut_oi":77267300,"fut_oi_change":-389500,"fut_turnover":4854310665,"opt_volume":43658,"opt_oi":59002600,"opt_turnover":25963534485,"ce_volume":35320,"pe_volume":8338},"SONACOMS":{"eq_volume":748268,"eq_turnover":380285732.6,"eq_high":515.05,"eq_low":502.7,"eq_close":510.3,"fut_volume":1413,"fut_oi":12082175,"fut_oi_change":15925,"fut_turnover":881285335,"opt_volume":5041,"opt_oi":8559075,"opt_turnover":3303177342.5,"ce_volume":3021,"pe_volume":2020},"AXISBANK":{"eq_volume":9663320,"eq_turnover":11982108785.6,"eq_high":1251.1,"eq_low":1231.8,"eq_close":1234.5,"fut_volume":14564,"fut_oi":56565000,"fut_oi_change":597500,"fut_turnover":11334666687.5,"opt_volume":76500,"opt_oi":33896875,"opt_turnover":61602894656.25,"ce_volume":46423,"pe_volume":30077},"ETERNAL":{"eq_volume":65732459,"eq_turnover":14381731753.83,"eq_high":223.85,"eq_low":213.06,"eq_close":221.17,"fut_volume":18854,"fut_oi":259331925,"fut_oi_change":555325,"fut_turnover":10045788898,"opt_volume":105930,"opt_oi":193379200,"opt_turnover":58668033948.25,"ce_volume":47963,"pe_volume":57967},"HINDPETRO":{"eq_volume":8573492,"eq_turnover":3264947719.05,"eq_high":388.85,"eq_low":367.5,"eq_close":384.35,"fut_volume":8450,"fut_oi":47466000,"fut_oi_change":3073950,"fut_turnover":6480044955,"opt_volume":26130,"opt_oi":35182350,"opt_turnover":20998884285,"ce_volume":13931,"pe_volume":12199},"IDFCFIRSTB":{"eq_volume":34060333,"eq_turnover":2212667897.39,"eq_high":65.68,"eq_low":64.12,"eq_close":64.78,"fut_volume":6377,"fut_oi":463759275,"fut_oi_change":-1901375,"fut_turnover":3853525894.75,"opt_volume":28078,"opt_oi":524334300,"opt_turnover":18195918898.5,"ce_volume":16400,"pe_volume":11678},"TVSMOTOR":{"eq_volume":2588732,"eq_turnover":8927218754.4,"eq_high":3564.8,"eq_low":3402.8,"eq_close":3422.6,"fut_volume":11532,"fut_oi":8511125,"fut_oi_change":449050,"fut_turnover":6988475795,"opt_volume":48867,"opt_oi":4701200,"opt_turnover":31213336420,"ce_volume":25226,"pe_volume":23641},"LODHA":{"eq_volume":728482,"eq_turnover":636021793.2,"eq_high":887.05,"eq_low":860.35,"eq_close":869.05,"fut_volume":1722,"fut_oi":9519750,"fut_oi_change":72000,"fut_turnover":677919307.5,"opt_volume":5780,"opt_oi":5393250,"opt_turnover":2425568670,"ce_volume":3736,"pe_volume":2044},"BAJAJ-AUTO":{"eq_volume":390062,"eq_turnover":3579270600.5,"eq_high":9280,"eq_low":9080,"eq_close":9162,"fut_volume":7808,"fut_oi":3246675,"fut_oi_change":45675,"fut_turnover":5357079000,"opt_volume":47184,"opt_oi":2597850,"opt_turnover":33707004168.75,"ce_volume":27676,"pe_volume":19508},"BOSCHLTD":{"eq_volume":27041,"eq_turnover":844051150,"eq_high":31620,"eq_low":30815,"eq_close":31305,"fut_volume":1460,"fut_oi":211275,"fut_oi_change":2150,"fut_turnover":1142539750,"opt_volume":6336,"opt_oi":383375,"opt_turnover":5278927986.25,"ce_volume":4055,"pe_volume":2281},"CIPLA":{"eq_volume":1405268,"eq_turnover":1865308392.4,"eq_high":1341.7,"eq_low":1319,"eq_close":1324.3,"fut_volume":3478,"fut_oi":12697875,"fut_oi_change":-76500,"fut_turnover":1736823450,"opt_volume":33037,"opt_oi":11706750,"opt_turnover":16861629956.25,"ce_volume":25002,"pe_volume":8035},"DLF":{"eq_volume":3176429,"eq_turnover":1785578539.15,"eq_high":571.75,"eq_low":555.55,"eq_close":558.1,"fut_volume":7519,"fut_oi":51098850,"fut_oi_change":673200,"fut_turnover":3496652981.25,"opt_volume":26461,"opt_oi":22567050,"opt_turnover":13010117133.75,"ce_volume":16132,"pe_volume":10329},"DRREDDY":{"eq_volume":1969692,"eq_turnover":2602743481.2,"eq_high":1337.3,"eq_low":1303.6,"eq_close":1319,"fut_volume":3716,"fut_oi":14682500,"fut_oi_change":-48750,"fut_turnover":3070486437.5,"opt_volume":23596,"opt_oi":14543125,"opt_turnover":19922287687.5,"ce_volume":17264,"pe_volume":6332},"EXIDEIND":{"eq_volume":1465707,"eq_turnover":453707358.75,"eq_high":314.45,"eq_low":304.5,"eq_close":310,"fut_volume":1410,"fut_oi":27732600,"fut_oi_change":-138600,"fut_turnover":786975570,"opt_volume":4069,"opt_oi":20799000,"opt_turnover":2393188560,"ce_volume":3067,"pe_volume":1002},"GODREJPROP":{"eq_volume":762875,"eq_turnover":1237122337.1,"eq_high":1649.6,"eq_low":1600.6,"eq_close":1616.3,"fut_volume":4160,"fut_oi":8396300,"fut_oi_change":132000,"fut_turnover":1861842702.5,"opt_volume":12662,"opt_oi":4853475,"opt_turnover":5991448375,"ce_volume":6854,"pe_volume":5808},"KOTAKBANK":{"eq_volume":25048123,"eq_turnover":9441227395.65,"eq_high":380.15,"eq_low":374.05,"eq_close":375.3,"fut_volume":10970,"fut_oi":217652000,"fut_oi_change":4186000,"fut_turnover":8303788000,"opt_volume":25220,"opt_oi":63574000,"opt_turnover":19796184200,"ce_volume":15526,"pe_volume":9694},"M&M":{"eq_volume":6968585,"eq_turnover":21299817984.8,"eq_high":3142.8,"eq_low":3020,"eq_close":3031.2,"fut_volume":16422,"fut_oi":17858200,"fut_oi_change":558400,"fut_turnover":10083977440,"opt_volume":97537,"opt_oi":10291800,"opt_turnover":62787711560,"ce_volume":53531,"pe_volume":44006},"NATIONALUM":{"eq_volume":20128518,"eq_turnover":8051265771.45,"eq_high":410.2,"eq_low":385.95,"eq_close":409.15,"fut_volume":8388,"fut_oi":46372500,"fut_oi_change":-307500,"fut_turnover":12573354187.5,"opt_volume":35766,"opt_oi":71647500,"opt_turnover":55948602750,"ce_volume":24384,"pe_volume":11382},"NHPC":{"eq_volume":16804967,"eq_turnover":1257553690.52,"eq_high":76.36,"eq_low":72.76,"eq_close":74.78,"fut_volume":2894,"fut_oi":72108800,"fut_oi_change":614400,"fut_turnover":1392724864,"opt_volume":14248,"opt_oi":58726400,"opt_turnover":7103059200,"ce_volume":10871,"pe_volume":3377},"PAYTM":{"eq_volume":2037889,"eq_turnover":2058750976.4,"eq_high":1025.8,"eq_low":997.7,"eq_close":1009.1,"fut_volume":2997,"fut_oi":21110550,"fut_oi_change":0,"fut_turnover":2202066425,"opt_volume":12529,"opt_oi":14273075,"opt_turnover":9739005620,"ce_volume":7740,"pe_volume":4789},"PGEL":{"eq_volume":3360029,"eq_turnover":1801807186,"eq_high":546.8,"eq_low":527,"eq_close":532.2,"fut_volume":4917,"fut_oi":13555550,"fut_oi_change":-592800,"fut_turnover":2506194382.5,"opt_volume":19027,"opt_oi":13958350,"opt_turnover":10282975845,"ce_volume":10929,"pe_volume":8098},"TECHM":{"eq_volume":3067753,"eq_turnover":4129466417,"eq_high":1356.5,"eq_low":1327,"eq_close":1349.8,"fut_volume":5176,"fut_oi":18334200,"fut_oi_change":-471000,"fut_turnover":4184909340,"opt_volume":24516,"opt_oi":15263400,"opt_turnover":20552476890,"ce_volume":18183,"pe_volume":6333},"ULTRACEMCO":{"eq_volume":535730,"eq_turnover":5992853693,"eq_high":11405,"eq_low":11059,"eq_close":11089,"fut_volume":6621,"fut_oi":2125700,"fut_oi_change":48550,"fut_turnover":3719963450,"opt_volume":25955,"opt_oi":1271600,"opt_turnover":15596679812.5,"ce_volume":18300,"pe_volume":7655},"BANKINDIA":{"eq_volume":6364616,"eq_turnover":977155427.06,"eq_high":156.6,"eq_low":149.81,"eq_close":154.78,"fut_volume":1854,"fut_oi":53492400,"fut_oi_change":-650000,"fut_turnover":1480276772,"opt_volume":3833,"opt_oi":47044400,"opt_turnover":3206388900,"ce_volume":2495,"pe_volume":1338},"BIOCON":{"eq_volume":1921703,"eq_turnover":754795818.2,"eq_high":397.5,"eq_low":389,"eq_close":392.2,"fut_volume":2623,"fut_oi":34722500,"fut_oi_change":-445000,"fut_turnover":2581453875,"opt_volume":14372,"opt_oi":32507500,"opt_turnover":14529127375,"ce_volume":9379,"pe_volume":4993},"COALINDIA":{"eq_volume":27328045,"eq_turnover":12704311424.8,"eq_high":474,"eq_low":445,"eq_close":470.1,"fut_volume":19872,"fut_oi":43447050,"fut_oi_change":2259900,"fut_turnover":12442695390,"opt_volume":211116,"opt_oi":64480050,"opt_turnover":135428841540,"ce_volume":150525,"pe_volume":60591},"COLPAL":{"eq_volume":836489,"eq_turnover":1665406549.2,"eq_high":2040,"eq_low":1962.2,"eq_close":1975.8,"fut_volume":8675,"fut_oi":6167025,"fut_oi_change":229950,"fut_turnover":3883040010,"opt_volume":48175,"opt_oi":6808050,"opt_turnover":22745844483.75,"ce_volume":29772,"pe_volume":18403},"FEDERALBNK":{"eq_volume":7972457,"eq_turnover":2150220179,"eq_high":272.15,"eq_low":264.85,"eq_close":270.25,"fut_volume":4037,"fut_oi":79605000,"fut_oi_change":2245000,"fut_turnover":5461522750,"opt_volume":19289,"opt_oi":95115000,"opt_turnover":27688624000,"ce_volume":13706,"pe_volume":5583},"KPITTECH":{"eq_volume":1341404,"eq_turnover":904537013.8,"eq_high":683.7,"eq_low":665.65,"eq_close":671.25,"fut_volume":2268,"fut_oi":7301925,"fut_oi_change":100300,"fut_turnover":650386573.75,"opt_volume":14045,"opt_oi":8981525,"opt_turnover":4424616222.5,"ce_volume":11360,"pe_volume":2685},"LT":{"eq_volume":4255443,"eq_turnover":16003610914.2,"eq_high":3830,"eq_low":3704.9,"eq_close":3719.5,"fut_volume":16932,"fut_oi":13616225,"fut_oi_change":485975,"fut_turnover":11168285992.5,"opt_volume":106119,"opt_oi":18890375,"opt_turnover":72747607152.5,"ce_volume":66082,"pe_volume":40037},"NMDC":{"eq_volume":20967907,"eq_turnover":1676516221.39,"eq_high":81.6,"eq_low":77.54,"eq_close":80.87,"fut_volume":4205,"fut_oi":323554500,"fut_oi_change":-5028750,"fut_turnover":2270720857.5,"opt_volume":13679,"opt_oi":133913250,"opt_turnover":7718860507.5,"ce_volume":10144,"pe_volume":3535},"OIL":{"eq_volume":5799980,"eq_turnover":2798572234.45,"eq_high":489.75,"eq_low":475.5,"eq_close":479.3,"fut_volume":4323,"fut_oi":23077600,"fut_oi_change":553000,"fut_turnover":2910444530,"opt_volume":26161,"opt_oi":30574600,"opt_turnover":18503160410,"ce_volume":20265,"pe_volume":5896},"PHOENIXLTD":{"eq_volume":473955,"eq_turnover":741215240.2,"eq_high":1579.4,"eq_low":1552,"eq_close":1560.2,"fut_volume":1732,"fut_oi":4063500,"fut_oi_change":14700,"fut_turnover":949500335,"opt_volume":2740,"opt_oi":1836800,"opt_turnover":1604796130,"ce_volume":2346,"pe_volume":394},"PIIND":{"eq_volume":196476,"eq_turnover":582902164.9,"eq_high":2997.2,"eq_low":2940.1,"eq_close":2952.4,"fut_volume":1862,"fut_oi":3169425,"fut_oi_change":-49000,"fut_turnover":968250675,"opt_volume":5998,"opt_oi":1188600,"opt_turnover":3238799226.25,"ce_volume":3966,"pe_volume":2032},"TATACONSUM":{"eq_volume":961388,"eq_turnover":1020463556,"eq_high":1072.8,"eq_low":1051.4,"eq_close":1057.8,"fut_volume":1876,"fut_oi":13004750,"fut_oi_change":-59400,"fut_turnover":1097944375,"opt_volume":5143,"opt_oi":4777300,"opt_turnover":3114424225,"ce_volume":2741,"pe_volume":2402},"WIPRO":{"eq_volume":19042475,"eq_turnover":3848750619,"eq_high":203.8,"eq_low":199.7,"eq_close":202.51,"fut_volume":9308,"fut_oi":157800000,"fut_oi_change":4506000,"fut_turnover":5625841620,"opt_volume":27818,"opt_oi":134532000,"opt_turnover":17425394190,"ce_volume":19256,"pe_volume":8562},"GODREJCP":{"eq_volume":6037448,"eq_turnover":6382328808.9,"eq_high":1096.2,"eq_low":1045.1,"eq_close":1052.3,"fut_volume":7046,"fut_oi":9182500,"fut_oi_change":525500,"fut_turnover":3738269500,"opt_volume":9247,"opt_oi":3528000,"opt_turnover":5167100100,"ce_volume":5140,"pe_volume":4107},"BHARATFORG":{"eq_volume":1253973,"eq_turnover":2199997085,"eq_high":1792.4,"eq_low":1720,"eq_close":1779.6,"fut_volume":6920,"fut_oi":6508500,"fut_oi_change":146500,"fut_turnover":6087464100,"opt_volume":32013,"opt_oi":7462500,"opt_turnover":29973943200,"ce_volume":18259,"pe_volume":13754},"INDUSTOWER":{"eq_volume":5403935,"eq_turnover":2379321551.35,"eq_high":444.75,"eq_low":430.55,"eq_close":442.05,"fut_volume":5727,"fut_oi":70907000,"fut_oi_change":-761600,"fut_turnover":4288647715,"opt_volume":18804,"opt_oi":20556400,"opt_turnover":14578866885,"ce_volume":11779,"pe_volume":7025},"PATANJALI":{"eq_volume":1877473,"eq_turnover":921130571.9,"eq_high":494.55,"eq_low":487.2,"eq_close":490.6,"fut_volume":4201,"fut_oi":37449900,"fut_oi_change":65700,"fut_turnover":1857583350,"opt_volume":5504,"opt_oi":5965200,"opt_turnover":2504340315,"ce_volume":3111,"pe_volume":2393},"POWERINDIA":{"eq_volume":142729,"eq_turnover":3539188940,"eq_high":25325,"eq_low":24385,"eq_close":24880,"fut_volume":2129,"fut_oi":296050,"fut_oi_change":9250,"fut_turnover":2651717250,"opt_volume":8620,"opt_oi":393600,"opt_turnover":11335360030,"ce_volume":6332,"pe_volume":2288},"SOLARINDS":{"eq_volume":145031,"eq_turnover":2105560754,"eq_high":14745,"eq_low":14315,"eq_close":14525,"fut_volume":2414,"fut_oi":604800,"fut_oi_change":-15050,"fut_turnover":1756148850,"opt_volume":10983,"opt_oi":699950,"opt_turnover":8296961367.5,"ce_volume":7736,"pe_volume":3247},"TATAPOWER":{"eq_volume":25007929,"eq_turnover":9993820025.9,"eq_high":407.35,"eq_low":383.45,"eq_close":402.15,"fut_volume":19907,"fut_oi":53259950,"fut_oi_change":4584900,"fut_turnover":11534269035,"opt_volume":198527,"opt_oi":59481900,"opt_turnover":118283618775,"ce_volume":145402,"pe_volume":53125},"VOLTAS":{"eq_volume":799532,"eq_turnover":1157108304,"eq_high":1474.8,"eq_low":1420,"eq_close":1449.4,"fut_volume":5846,"fut_oi":9886500,"fut_oi_change":202125,"fut_turnover":3161398050,"opt_volume":27487,"opt_oi":9046875,"opt_turnover":15725480100,"ce_volume":20485,"pe_volume":7002},"CROMPTON":{"eq_volume":2440630,"eq_turnover":606693168.7,"eq_high":254.5,"eq_low":243,"eq_close":247.2,"fut_volume":3328,"fut_oi":45842400,"fut_oi_change":-43200,"fut_turnover":1494162000,"opt_volume":8577,"opt_oi":14988600,"opt_turnover":4011681510,"ce_volume":6684,"pe_volume":1893},"APOLLOHOSP":{"eq_volume":550020,"eq_turnover":4170187557,"eq_high":7662.5,"eq_low":7542.5,"eq_close":7574.5,"fut_volume":3542,"fut_oi":2405500,"fut_oi_change":-67750,"fut_turnover":3361846312.5,"opt_volume":16532,"opt_oi":1836250,"opt_turnover":16181259331.25,"ce_volume":10636,"pe_volume":5896},"FORTIS":{"eq_volume":2366155,"eq_turnover":2035075998,"eq_high":875.05,"eq_low":852,"eq_close":859.5,"fut_volume":2502,"fut_oi":11710250,"fut_oi_change":375875,"fut_turnover":1674408463.75,"opt_volume":4304,"opt_oi":6012450,"opt_turnover":3067699317.5,"ce_volume":3344,"pe_volume":960},"GLENMARK":{"eq_volume":996025,"eq_turnover":2233907259.6,"eq_high":2273.2,"eq_low":2215.4,"eq_close":2256.4,"fut_volume":4145,"fut_oi":11526000,"fut_oi_change":-25125,"fut_turnover":3497252025,"opt_volume":14366,"opt_oi":3276750,"opt_turnover":12438296006.25,"ce_volume":8331,"pe_volume":6035},"HUDCO":{"eq_volume":2582752,"eq_turnover":456149002.49,"eq_high":179.47,"eq_low":173.75,"eq_close":176.66,"fut_volume":1126,"fut_oi":38050800,"fut_oi_change":-349650,"fut_turnover":553587580.5,"opt_volume":4018,"opt_oi":34004850,"opt_turnover":2089147122.75,"ce_volume":3133,"pe_volume":885},"ICICIPRULI":{"eq_volume":949805,"eq_turnover":562683482.75,"eq_high":596.65,"eq_low":583.15,"eq_close":592.95,"fut_volume":1184,"fut_oi":16820200,"fut_oi_change":-57350,"fut_turnover":648659025,"opt_volume":3189,"opt_oi":5844150,"opt_turnover":1816859562.5,"ce_volume":1718,"pe_volume":1471},"IDEA":{"eq_volume":444257788,"eq_turnover":4243742179.67,"eq_high":9.74,"eq_low":9.36,"eq_close":9.56,"fut_volume":7872,"fut_oi":6618942375,"fut_oi_change":-167608875,"fut_turnover":5372552748,"opt_volume":21434,"opt_oi":2984367150,"opt_turnover":16351670967.75,"ce_volume":15276,"pe_volume":6158},"NBCC":{"eq_volume":9325823,"eq_turnover":804631281.17,"eq_high":87.98,"eq_low":84.41,"eq_close":86.58,"fut_volume":1359,"fut_oi":83213000,"fut_oi_change":552500,"fut_turnover":765931010,"opt_volume":3181,"opt_oi":54704000,"opt_turnover":1901402490,"ce_volume":2093,"pe_volume":1088},"POLYCAB":{"eq_volume":498945,"eq_turnover":3708869380,"eq_high":7538,"eq_low":7282,"eq_close":7455,"fut_volume":6562,"fut_oi":1934250,"fut_oi_change":-44750,"fut_turnover":6113723062.5,"opt_volume":42578,"opt_oi":3426375,"opt_turnover":41804044537.5,"ce_volume":25697,"pe_volume":16881},"DELHIVERY":{"eq_volume":1659934,"eq_turnover":678100982.35,"eq_high":415,"eq_low":403.8,"eq_close":408.2,"fut_volume":1538,"fut_oi":24505750,"fut_oi_change":902625,"fut_turnover":1310323075,"opt_volume":4398,"opt_oi":11298375,"opt_turnover":3948957815,"ce_volume":2564,"pe_volume":1834},"DIXON":{"eq_volume":968428,"eq_turnover":10267985685,"eq_high":10849,"eq_low":10254,"eq_close":10803,"fut_volume":19805,"fut_oi":2486850,"fut_oi_change":-12450,"fut_turnover":10445051600,"opt_volume":183171,"opt_oi":3822800,"opt_turnover":102892425570,"ce_volume":131711,"pe_volume":51460},"HINDUNILVR":{"eq_volume":1791973,"eq_turnover":3817223090,"eq_high":2165.1,"eq_low":2109.3,"eq_close":2136.9,"fut_volume":5139,"fut_oi":15734400,"fut_oi_change":-60000,"fut_turnover":3292857570,"opt_volume":50747,"opt_oi":10192200,"opt_turnover":33768575805,"ce_volume":35064,"pe_volume":15683},"ALKEM":{"eq_volume":121868,"eq_turnover":664947280,"eq_high":5528,"eq_low":5400,"eq_close":5444,"fut_volume":1205,"fut_oi":1256250,"fut_oi_change":15750,"fut_turnover":824965562.5,"opt_volume":2471,"opt_oi":399875,"opt_turnover":1763929031.25,"ce_volume":1682,"pe_volume":789},"ASHOKLEY":{"eq_volume":44243228,"eq_turnover":7915757337.89,"eq_high":184.97,"eq_low":177.01,"eq_close":178.47,"fut_volume":10911,"fut_oi":148200000,"fut_oi_change":390000,"fut_turnover":9802114150,"opt_volume":44381,"opt_oi":120915000,"opt_turnover":42160918200,"ce_volume":26432,"pe_volume":17949},"ASTRAL":{"eq_volume":1565206,"eq_turnover":2623749594.6,"eq_high":1725,"eq_low":1633.1,"eq_close":1696,"fut_volume":5508,"fut_oi":10247600,"fut_oi_change":179350,"fut_turnover":3838771700,"opt_volume":47893,"opt_oi":4727700,"opt_turnover":34709122062.5,"ce_volume":27975,"pe_volume":19918},"BANKBARODA":{"eq_volume":8115474,"eq_turnover":2343559705.3,"eq_high":293.35,"eq_low":282.95,"eq_close":289.2,"fut_volume":4990,"fut_oi":85804875,"fut_oi_change":1550250,"fut_turnover":4219116963.75,"opt_volume":21798,"opt_oi":77591475,"opt_turnover":19157584680,"ce_volume":12765,"pe_volume":9033},"BPCL":{"eq_volume":11176171,"eq_turnover":3629316262.1,"eq_high":330.35,"eq_low":314,"eq_close":326.35,"fut_volume":4423,"fut_oi":45478325,"fut_oi_change":246875,"fut_turnover":2840827557.5,"opt_volume":30238,"opt_oi":43323600,"opt_turnover":20016670523.75,"ce_volume":15190,"pe_volume":15048},"CUMMINSIND":{"eq_volume":962205,"eq_turnover":4511527858.2,"eq_high":4781.3,"eq_low":4518,"eq_close":4753.6,"fut_volume":4463,"fut_oi":3432000,"fut_oi_change":-13600,"fut_turnover":4180233920,"opt_volume":25201,"opt_oi":1875000,"opt_turnover":24724901920,"ce_volume":17133,"pe_volume":8068},"DIVISLAB":{"eq_volume":153876,"eq_turnover":965465172.5,"eq_high":6330.5,"eq_low":6221,"eq_close":6282,"fut_volume":3765,"fut_oi":2592000,"fut_oi_change":-89500,"fut_turnover":2363683700,"opt_volume":15536,"opt_oi":1243500,"opt_turnover":10168814965,"ce_volume":10495,"pe_volume":5041},"IEX":{"eq_volume":5791203,"eq_turnover":705152270.72,"eq_high":124.48,"eq_low":119.87,"eq_close":122.76,"fut_volume":2147,"fut_oi":65505000,"fut_oi_change":-120000,"fut_turnover":983188762.5,"opt_volume":11022,"opt_oi":72570000,"opt_turnover":5329560712.5,"ce_volume":8706,"pe_volume":2316},"INDUSINDBK":{"eq_volume":7514347,"eq_turnover":6304451104.05,"eq_high":870.5,"eq_low":828,"eq_close":831.35,"fut_volume":17354,"fut_oi":36365700,"fut_oi_change":11200,"fut_turnover":10190136530,"opt_volume":64109,"opt_oi":16534700,"opt_turnover":39394464970,"ce_volume":32874,"pe_volume":31235},"KALYANKJIL":{"eq_volume":3218077,"eq_turnover":1247223302.2,"eq_high":393.65,"eq_low":378.6,"eq_close":389.95,"fut_volume":2575,"fut_oi":23749100,"fut_oi_change":-641550,"fut_turnover":1174426776.25,"opt_volume":10067,"opt_oi":14309150,"opt_turnover":4809036827.5,"ce_volume":6435,"pe_volume":3632},"LAURUSLABS":{"eq_volume":1300644,"eq_turnover":1348789996.5,"eq_high":1057,"eq_low":1017.6,"eq_close":1046.8,"fut_volume":3385,"fut_oi":18921000,"fut_oi_change":-141950,"fut_turnover":2986331690,"opt_volume":13585,"opt_oi":13713900,"opt_turnover":12478548802.5,"ce_volume":10014,"pe_volume":3571},"LTF":{"eq_volume":3821356,"eq_turnover":1014112254.8,"eq_high":269.35,"eq_low":260.75,"eq_close":265.5,"fut_volume":4487,"fut_oi":55806750,"fut_oi_change":-1003500,"fut_turnover":2681999887.5,"opt_volume":13907,"opt_oi":59944500,"opt_turnover":8971563375,"ce_volume":10322,"pe_volume":3585},"MANAPPURAM":{"eq_volume":4928562,"eq_turnover":1263269617.5,"eq_high":259.35,"eq_low":250.95,"eq_close":255.55,"fut_volume":2666,"fut_oi":55644000,"fut_oi_change":1797000,"fut_turnover":2055826500,"opt_volume":3719,"opt_oi":44643000,"opt_turnover":3055002000,"ce_volume":2538,"pe_volume":1181},"MARICO":{"eq_volume":4308894,"eq_turnover":3261806154.35,"eq_high":764.3,"eq_low":749.35,"eq_close":757.15,"fut_volume":7370,"fut_oi":25130400,"fut_oi_change":-678000,"fut_turnover":6688330140,"opt_volume":29032,"opt_oi":9264000,"opt_turnover":27019093980,"ce_volume":14581,"pe_volume":14451},"MOTHERSON":{"eq_volume":24171355,"eq_turnover":2882189789.72,"eq_high":120.83,"eq_low":116.64,"eq_close":120.17,"fut_volume":5825,"fut_oi":122348100,"fut_oi_change":-5485800,"fut_turnover":4248784941,"opt_volume":9961,"opt_oi":83264850,"opt_turnover":7666072600.5,"ce_volume":5959,"pe_volume":4002},"SRF":{"eq_volume":1288113,"eq_turnover":3310682348.9,"eq_high":2636.8,"eq_low":2446.6,"eq_close":2626.3,"fut_volume":8255,"fut_oi":3453600,"fut_oi_change":-169200,"fut_turnover":4243101280,"opt_volume":53820,"opt_oi":3003200,"opt_turnover":28643057770,"ce_volume":36567,"pe_volume":17253},"SWIGGY":{"eq_volume":14050937,"eq_turnover":3932145826.6,"eq_high":285.6,"eq_low":271.1,"eq_close":280.9,"fut_volume":8289,"fut_oi":50599900,"fut_oi_change":-32500,"fut_turnover":3006393715,"opt_volume":21240,"opt_oi":14951300,"opt_turnover":7885084740,"ce_volume":7415,"pe_volume":13825},"ZYDUSLIFE":{"eq_volume":462276,"eq_turnover":424271920.45,"eq_high":926.6,"eq_low":909.5,"eq_close":916.9,"fut_volume":1175,"fut_oi":9218700,"fut_oi_change":27000,"fut_turnover":974236815,"opt_volume":3565,"opt_oi":7114500,"opt_turnover":3054737835,"ce_volume":2623,"pe_volume":942},"BHARTIARTL":{"eq_volume":12922735,"eq_turnover":23285924604.3,"eq_high":1817.8,"eq_low":1791,"eq_close":1801.3,"fut_volume":12069,"fut_oi":58908550,"fut_oi_change":-1064950,"fut_turnover":10374659300,"opt_volume":68449,"opt_oi":32722275,"opt_turnover":60898699846.25,"ce_volume":45074,"pe_volume":23375},"CHOLAFIN":{"eq_volume":2352076,"eq_turnover":3600020247.3,"eq_high":1552.3,"eq_low":1510,"eq_close":1526.1,"fut_volume":3749,"fut_oi":16931250,"fut_oi_change":431875,"fut_turnover":3598046750,"opt_volume":11523,"opt_oi":7448125,"opt_turnover":11583438843.75,"ce_volume":6454,"pe_volume":5069},"JSWENERGY":{"eq_volume":19316979,"eq_turnover":10018020026.3,"eq_high":528,"eq_low":484,"eq_close":518.3,"fut_volume":12244,"fut_oi":26106000,"fut_oi_change":-1167000,"fut_turnover":6316219000,"opt_volume":98418,"opt_oi":12814000,"opt_turnover":52448255450,"ce_volume":77482,"pe_volume":20936},"RELIANCE":{"eq_volume":20939959,"eq_turnover":29264877793.7,"eq_high":1410.9,"eq_low":1381.1,"eq_close":1392.2,"fut_volume":34916,"fut_oi":98882500,"fut_oi_change":820500,"fut_turnover":24453705050,"opt_volume":430721,"opt_oi":120531500,"opt_turnover":309386657225,"ce_volume":288260,"pe_volume":142461},"ADANIGREEN":{"eq_volume":6591414,"eq_turnover":5687996086.6,"eq_high":881.95,"eq_low":837.4,"eq_close":866.55,"fut_volume":8339,"fut_oi":19513200,"fut_oi_change":528600,"fut_turnover":4337298240,"opt_volume":29110,"opt_oi":15043200,"opt_turnover":16066471800,"ce_volume":22732,"pe_volume":6378},"ADANIPORTS":{"eq_volume":2699173,"eq_turnover":3774615043.6,"eq_high":1418.6,"eq_low":1375.3,"eq_close":1391.5,"fut_volume":5458,"fut_oi":20989775,"fut_oi_change":186200,"fut_turnover":3635974757.5,"opt_volume":37935,"opt_oi":15859300,"opt_turnover":26198699575,"ce_volume":19569,"pe_volume":18366},"BAJAJFINSV":{"eq_volume":1095963,"eq_turnover":1945841337.4,"eq_high":1794.4,"eq_low":1763.1,"eq_close":1770.8,"fut_volume":4720,"fut_oi":12521500,"fut_oi_change":-150250,"fut_turnover":2100672525,"opt_volume":35219,"opt_oi":13528000,"opt_turnover":16373295737.5,"ce_volume":23491,"pe_volume":11728},"BLUESTARCO":{"eq_volume":638482,"eq_turnover":1240136889.5,"eq_high":1969.5,"eq_low":1892,"eq_close":1953.5,"fut_volume":3453,"fut_oi":2296775,"fut_oi_change":-42250,"fut_turnover":2174300245,"opt_volume":8942,"opt_oi":2089750,"opt_turnover":5950837928.75,"ce_volume":7478,"pe_volume":1464},"HDFCAMC":{"eq_volume":848681,"eq_turnover":2076258668.7,"eq_high":2479.4,"eq_low":2408.4,"eq_close":2429,"fut_volume":2765,"fut_oi":5539500,"fut_oi_change":-8700,"fut_turnover":2032222110,"opt_volume":6140,"opt_oi":2654700,"opt_turnover":4715967060,"ce_volume":3997,"pe_volume":2143},"IOC":{"eq_volume":21636039,"eq_turnover":3439414477.26,"eq_high":162.25,"eq_low":154.06,"eq_close":160.16,"fut_volume":4424,"fut_oi":96135000,"fut_oi_change":-979875,"fut_turnover":3435519701.25,"opt_volume":23850,"opt_oi":131976000,"opt_turnover":19157562157.5,"ce_volume":11895,"pe_volume":11955},"ITC":{"eq_volume":23319679,"eq_turnover":7133363402.95,"eq_high":308,"eq_low":302.85,"eq_close":304.1,"fut_volume":7554,"fut_oi":154356800,"fut_oi_change":-1476800,"fut_turnover":3703486400,"opt_volume":59644,"opt_oi":176662400,"opt_turnover":30599978000,"ce_volume":44227,"pe_volume":15417},"MAXHEALTH":{"eq_volume":5744427,"eq_turnover":5870184596.1,"eq_high":1031.6,"eq_low":1008.8,"eq_close":1020.4,"fut_volume":2917,"fut_oi":13265175,"fut_oi_change":-157500,"fut_turnover":1566420975,"opt_volume":9237,"opt_oi":4947600,"opt_turnover":5155009571.25,"ce_volume":5333,"pe_volume":3904},"OFSS":{"eq_volume":82424,"eq_turnover":553587093,"eq_high":6796,"eq_low":6667,"eq_close":6694.5,"fut_volume":1816,"fut_oi":1499475,"fut_oi_change":-450,"fut_turnover":912399300,"opt_volume":15849,"opt_oi":888450,"opt_turnover":7842108686.25,"ce_volume":7438,"pe_volume":8411},"PIDILITIND":{"eq_volume":724869,"eq_turnover":1005647264.3,"eq_high":1397.8,"eq_low":1378,"eq_close":1387.4,"fut_volume":1196,"fut_oi":8041500,"fut_oi_change":19500,"fut_turnover":829219400,"opt_volume":2998,"opt_oi":2752000,"opt_turnover":2143854050,"ce_volume":1583,"pe_volume":1415},"SBIN":{"eq_volume":14614140,"eq_turnover":15790003178.6,"eq_high":1098,"eq_low":1070.5,"eq_close":1085.2,"fut_volume":20214,"fut_oi":69006750,"fut_oi_change":1838250,"fut_turnover":16451206125,"opt_volume":165906,"opt_oi":91494000,"opt_turnover":139937936700,"ce_volume":98209,"pe_volume":67697},"DABUR":{"eq_volume":1756738,"eq_turnover":807850868.45,"eq_high":471.3,"eq_low":456.5,"eq_close":459.35,"fut_volume":1855,"fut_oi":25122500,"fut_oi_change":340000,"fut_turnover":1071778750,"opt_volume":11442,"opt_oi":17646250,"opt_turnover":6925415937.5,"ce_volume":6029,"pe_volume":5413},"360ONE":{"eq_volume":934229,"eq_turnover":968891564.9,"eq_high":1049.1,"eq_low":1017.3,"eq_close":1043.4,"fut_volume":1506,"fut_oi":2990500,"fut_oi_change":-1500,"fut_turnover":782861300,"opt_volume":2855,"opt_oi":1669000,"opt_turnover":1547519325,"ce_volume":1969,"pe_volume":886},"ADANIENT":{"eq_volume":1473773,"eq_turnover":2942527760.3,"eq_high":2026,"eq_low":1947.1,"eq_close":2002,"fut_volume":7006,"fut_oi":15574527,"fut_oi_change":-573195,"fut_turnover":4319676624,"opt_volume":42428,"opt_oi":12479892,"opt_turnover":27436978058.250008,"ce_volume":28245,"pe_volume":14183},"JSWSTEEL":{"eq_volume":1265744,"eq_turnover":1478064653.3,"eq_high":1182.5,"eq_low":1150,"eq_close":1172.6,"fut_volume":5171,"fut_oi":45696150,"fut_oi_change":-745875,"fut_turnover":4069520257.5,"opt_volume":12872,"opt_oi":10919475,"opt_turnover":10719394200,"ce_volume":8242,"pe_volume":4630},"POLICYBZR":{"eq_volume":1247017,"eq_turnover":1819066407.1,"eq_high":1474,"eq_low":1435.5,"eq_close":1462.7,"fut_volume":2747,"fut_oi":7510650,"fut_oi_change":-150850,"fut_turnover":1404104870,"opt_volume":4642,"opt_oi":4054050,"opt_turnover":2427214545,"ce_volume":2296,"pe_volume":2346},"PREMIERENE":{"eq_volume":1671737,"eq_turnover":1311331298.6,"eq_high":794.35,"eq_low":767.25,"eq_close":789.35,"fut_volume":3552,"fut_oi":7901650,"fut_oi_change":-33350,"fut_turnover":1587292991.25,"opt_volume":13560,"opt_oi":6702200,"opt_turnover":6277502642.5,"ce_volume":9371,"pe_volume":4189},"SUZLON":{"eq_volume":108432510,"eq_turnover":4614714717.16,"eq_high":43.54,"eq_low":40.93,"eq_close":42.43,"fut_volume":6855,"fut_oi":284540200,"fut_oi_change":-7824675,"fut_turnover":2636721979,"opt_volume":42440,"opt_oi":292509275,"opt_turnover":17420809399.75,"ce_volume":34389,"pe_volume":8051},"UPL":{"eq_volume":1299556,"eq_turnover":814976690.7,"eq_high":633.75,"eq_low":616.95,"eq_close":629.05,"fut_volume":1966,"fut_oi":29880460,"fut_oi_change":-119240,"fut_turnover":1674928304.75,"opt_volume":8341,"opt_oi":28869630,"opt_turnover":7390417355.25,"ce_volume":5419,"pe_volume":2922},"VEDL":{"eq_volume":10180516,"eq_turnover":7272711059.85,"eq_high":730.3,"eq_low":704.55,"eq_close":719.6,"fut_volume":9896,"fut_oi":60120850,"fut_oi_change":415150,"fut_turnover":8091551340,"opt_volume":57450,"opt_oi":57847300,"opt_turnover":49029185502.5,"ce_volume":38203,"pe_volume":19247},"LICI":{"eq_volume":755710,"eq_turnover":602859985.55,"eq_high":808,"eq_low":791.55,"eq_close":796.65,"fut_volume":1479,"fut_oi":8857100,"fut_oi_change":91000,"fut_turnover":827108835,"opt_volume":4802,"opt_oi":9156000,"opt_turnover":2809054395,"ce_volume":3175,"pe_volume":1627},"SAIL":{"eq_volume":9824998,"eq_turnover":1494541845.06,"eq_high":154.2,"eq_low":149.6,"eq_close":153.65,"fut_volume":310,"fut_oi":174313600,"fut_oi_change":-935300,"fut_turnover":222838515,"opt_volume":86,"opt_oi":37205200,"opt_turnover":65118077,"ce_volume":34,"pe_volume":52},"ASIANPAINT":{"eq_volume":1384055,"eq_turnover":3079904845.5,"eq_high":2249.9,"eq_low":2201,"eq_close":2221.2,"fut_volume":4595,"fut_oi":13344500,"fut_oi_change":-95000,"fut_turnover":2564868775,"opt_volume":39031,"opt_oi":9638750,"opt_turnover":22242274300,"ce_volume":19015,"pe_volume":20016},"BRITANNIA":{"eq_volume":996754,"eq_turnover":5755360219,"eq_high":5910,"eq_low":5713,"eq_close":5787,"fut_volume":7711,"fut_oi":2816250,"fut_oi_change":-271500,"fut_turnover":5571801062.5,"opt_volume":19487,"opt_oi":1213125,"opt_turnover":14253607231.25,"ce_volume":9093,"pe_volume":10394},"GRASIM":{"eq_volume":952036,"eq_turnover":2559252637,"eq_high":2727.4,"eq_low":2660.6,"eq_close":2673.1,"fut_volume":4315,"fut_oi":14845500,"fut_oi_change":-61500,"fut_turnover":2902484150,"opt_volume":9686,"opt_oi":3105500,"opt_turnover":6726382475,"ce_volume":5667,"pe_volume":4019},"HDFCLIFE":{"eq_volume":3339906,"eq_turnover":2150063037.85,"eq_high":649.35,"eq_low":636.1,"eq_close":645.7,"fut_volume":1976,"fut_oi":36470500,"fut_oi_change":-126500,"fut_turnover":1401268990,"opt_volume":9854,"opt_oi":19932000,"opt_turnover":7408399900,"ce_volume":6976,"pe_volume":2878},"ICICIBANK":{"eq_volume":19676187,"eq_turnover":24999530425.9,"eq_high":1280.5,"eq_low":1258.3,"eq_close":1266.5,"fut_volume":23853,"fut_oi":120179500,"fut_oi_change":2665600,"fut_turnover":21286498100,"opt_volume":103966,"opt_oi":54968200,"opt_turnover":95809919625,"ce_volume":67418,"pe_volume":36548},"ICICIGI":{"eq_volume":606686,"eq_turnover":1123240306,"eq_high":1872.9,"eq_low":1840.2,"eq_close":1855.3,"fut_volume":1685,"fut_oi":4801550,"fut_oi_change":36400,"fut_turnover":1016469610,"opt_volume":5240,"opt_oi":1937975,"opt_turnover":3276708028.75,"ce_volume":3861,"pe_volume":1379},"INFY":{"eq_volume":7599940,"eq_turnover":9639108719,"eq_high":1278.6,"eq_low":1258,"eq_close":1265.8,"fut_volume":22018,"fut_oi":70228800,"fut_oi_change":-2154800,"fut_turnover":11191241400,"opt_volume":105842,"opt_oi":60992000,"opt_turnover":56774322420,"ce_volume":69517,"pe_volume":36325},"KFINTECH":{"eq_volume":497202,"eq_turnover":452799129.95,"eq_high":922.95,"eq_low":900.85,"eq_close":907.6,"fut_volume":1826,"fut_oi":2168500,"fut_oi_change":-17500,"fut_turnover":834274300,"opt_volume":3136,"opt_oi":3006000,"opt_turnover":1506527450,"ce_volume":1910,"pe_volume":1226},"MARUTI":{"eq_volume":544683,"eq_turnover":7152895645,"eq_high":13430,"eq_low":12966,"eq_close":13011,"fut_volume":13447,"fut_oi":2756800,"fut_oi_change":52100,"fut_turnover":8873058000,"opt_volume":132323,"opt_oi":3806650,"opt_turnover":91519073580,"ce_volume":77378,"pe_volume":54945},"MUTHOOTFIN":{"eq_volume":1798792,"eq_turnover":5718762327.2,"eq_high":3253.4,"eq_low":3119.1,"eq_close":3244,"fut_volume":3724,"fut_oi":3711950,"fut_oi_change":-11275,"fut_turnover":3281715030,"opt_volume":19236,"opt_oi":5837150,"opt_turnover":17871787711.25,"ce_volume":13607,"pe_volume":5629},"PFC":{"eq_volume":8640995,"eq_turnover":3554806269.75,"eq_high":421.35,"eq_low":398,"eq_close":415.9,"fut_volume":11348,"fut_oi":54450500,"fut_oi_change":1833000,"fut_turnover":6054256130,"opt_volume":53705,"opt_oi":54745600,"opt_turnover":29714158630,"ce_volume":37911,"pe_volume":15794},"SAMMAANCAP":{"eq_volume":4852687,"eq_turnover":693941643.98,"eq_high":145,"eq_low":141.91,"eq_close":142.42,"fut_volume":135,"fut_oi":105724100,"fut_oi_change":-352600,"fut_turnover":82806046,"opt_volume":26,"opt_oi":33260500,"opt_turnover":18292630,"ce_volume":24,"pe_volume":2},"SUPREMEIND":{"eq_volume":398294,"eq_turnover":1601412246.6,"eq_high":4060,"eq_low":3925.1,"eq_close":4043.7,"fut_volume":3366,"fut_oi":1878275,"fut_oi_change":173775,"fut_turnover":2360080187.5,"opt_volume":9098,"opt_oi":862575,"opt_turnover":6540374522.5,"ce_volume":6493,"pe_volume":2605},"TORNTPOWER":{"eq_volume":916861,"eq_turnover":1366382698,"eq_high":1517.4,"eq_low":1432.7,"eq_close":1506,"fut_volume":2940,"fut_oi":3506675,"fut_oi_change":72250,"fut_turnover":1868353380,"opt_volume":22175,"opt_oi":2705125,"opt_turnover":14721649396.25,"ce_volume":17986,"pe_volume":4189},"UNOMINDA":{"eq_volume":1101168,"eq_turnover":1175332117.2,"eq_high":1084.7,"eq_low":1047,"eq_close":1068.5,"fut_volume":1811,"fut_oi":5927350,"fut_oi_change":-146850,"fut_turnover":1061796505,"opt_volume":5655,"opt_oi":3212550,"opt_turnover":3471283942.5,"ce_volume":3255,"pe_volume":2400},"SUNPHARMA":{"eq_volume":2606057,"eq_turnover":4756869064.9,"eq_high":1833.6,"eq_low":1808.4,"eq_close":1825.3,"fut_volume":7143,"fut_oi":22230950,"fut_oi_change":-168700,"fut_turnover":4566730910,"opt_volume":49469,"opt_oi":21265650,"opt_turnover":31861637325,"ce_volume":29792,"pe_volume":19677},"SYNGENE":{"eq_volume":632047,"eq_turnover":254843403.9,"eq_high":408.6,"eq_low":396.2,"eq_close":404.1,"fut_volume":1443,"fut_oi":8649000,"fut_oi_change":-75000,"fut_turnover":583231950,"opt_volume":4675,"opt_oi":8459000,"opt_turnover":1973611800,"ce_volume":2759,"pe_volume":1916},"COFORGE":{"eq_volume":4181637,"eq_turnover":4619736481.7,"eq_high":1128.1,"eq_low":1078.5,"eq_close":1107.9,"fut_volume":11578,"fut_oi":25632000,"fut_oi_change":162000,"fut_turnover":4814622562.5,"opt_volume":54664,"opt_oi":18448875,"opt_turnover":24313423875,"ce_volume":37974,"pe_volume":16690},"GAIL":{"eq_volume":16072499,"eq_turnover":2430810138.38,"eq_high":153.93,"eq_low":144.67,"eq_close":152.35,"fut_volume":4997,"fut_oi":100976400,"fut_oi_change":1165500,"fut_turnover":2390376397.5,"opt_volume":23336,"opt_oi":77543550,"opt_turnover":11660534802,"ce_volume":16676,"pe_volume":6660},"HAVELLS":{"eq_volume":853612,"eq_turnover":1156020462.4,"eq_high":1364.6,"eq_low":1334.5,"eq_close":1354,"fut_volume":2577,"fut_oi":8902500,"fut_oi_change":-152500,"fut_turnover":1743692950,"opt_volume":8568,"opt_oi":4536000,"opt_turnover":5971857325,"ce_volume":5110,"pe_volume":3458},"HDFCBANK":{"eq_volume":46107561,"eq_turnover":38354969893,"eq_high":836.4,"eq_low":820.1,"eq_close":832.75,"fut_volume":46731,"fut_oi":283992500,"fut_oi_change":-8562400,"fut_turnover":21476386882.5,"opt_volume":172530,"opt_oi":133174800,"opt_turnover":81694282202.5,"ce_volume":109798,"pe_volume":62732},"HEROMOTOCO":{"eq_volume":476478,"eq_turnover":2592383201,"eq_high":5589,"eq_low":5376,"eq_close":5394.5,"fut_volume":5348,"fut_oi":3532050,"fut_oi_change":-9900,"fut_turnover":4365672525,"opt_volume":34517,"opt_oi":3229200,"opt_turnover":29329128660,"ce_volume":20916,"pe_volume":13601},"MANKIND":{"eq_volume":310028,"eq_turnover":685909767.6,"eq_high":2243.5,"eq_low":2184.7,"eq_close":2207.9,"fut_volume":1621,"fut_oi":2603025,"fut_oi_change":10575,"fut_turnover":809964337.5,"opt_volume":4740,"opt_oi":1728000,"opt_turnover":2478823762.5,"ce_volume":3715,"pe_volume":1025},"MAZDOCK":{"eq_volume":2150371,"eq_turnover":5208429847.3,"eq_high":2470.9,"eq_low":2382,"eq_close":2443.3,"fut_volume":9239,"fut_oi":4299000,"fut_oi_change":306000,"fut_turnover":4506835340,"opt_volume":49537,"opt_oi":7418200,"opt_turnover":25235422590,"ce_volume":34636,"pe_volume":14901},"MCX":{"eq_volume":2510419,"eq_turnover":6291193675,"eq_high":2539.9,"eq_low":2466.9,"eq_close":2526.1,"fut_volume":4894,"fut_oi":12536250,"fut_oi_change":78750,"fut_turnover":7697975125,"opt_volume":21234,"opt_oi":13955625,"opt_turnover":34815805468.75,"ce_volume":12972,"pe_volume":8262},"NUVAMA":{"eq_volume":329254,"eq_turnover":391308187,"eq_high":1207.9,"eq_low":1175.6,"eq_close":1183.8,"fut_volume":1136,"fut_oi":2052500,"fut_oi_change":26500,"fut_turnover":676841900,"opt_volume":1552,"opt_oi":1416000,"opt_turnover":1013408725,"ce_volume":1201,"pe_volume":351},"PETRONET":{"eq_volume":8997138,"eq_turnover":2660038394.3,"eq_high":301.95,"eq_low":288.15,"eq_close":296.7,"fut_volume":4745,"fut_oi":25992000,"fut_oi_change":-714400,"fut_turnover":2660345420,"opt_volume":32028,"opt_oi":33008700,"opt_turnover":18726742665,"ce_volume":22754,"pe_volume":9274},"PPLPHARMA":{"eq_volume":8629241,"eq_turnover":1273667464.3,"eq_high":155.2,"eq_low":144.96,"eq_close":145.54,"fut_volume":2415,"fut_oi":15563625,"fut_oi_change":44625,"fut_turnover":938775757.5,"opt_volume":10334,"opt_oi":15442875,"opt_turnover":4194542388.75,"ce_volume":5009,"pe_volume":5325},"SIEMENS":{"eq_volume":361947,"eq_turnover":1196938155.3,"eq_high":3349.6,"eq_low":3219.6,"eq_close":3324.7,"fut_volume":3127,"fut_oi":2441425,"fut_oi_change":28875,"fut_turnover":1805930052.5,"opt_volume":26295,"opt_oi":2385775,"opt_turnover":15823887572.5,"ce_volume":19871,"pe_volume":6424},"UNITDSPR":{"eq_volume":842671,"eq_turnover":1145583612.5,"eq_high":1368.8,"eq_low":1341.1,"eq_close":1363.5,"fut_volume":3751,"fut_oi":10252000,"fut_oi_change":200400,"fut_turnover":2044417000,"opt_volume":10404,"opt_oi":5441200,"opt_turnover":5874855620,"ce_volume":6418,"pe_volume":3986},"AMBER":{"eq_volume":775004,"eq_turnover":5433487636.5,"eq_high":7305.5,"eq_low":6883.5,"eq_close":6929.5,"fut_volume":7498,"fut_oi":1172700,"fut_oi_change":117500,"fut_turnover":5261513900,"opt_volume":39561,"opt_oi":1795100,"opt_turnover":29702478100,"ce_volume":21915,"pe_volume":17646},"BAJFINANCE":{"eq_volume":15508258,"eq_turnover":13517084002.5,"eq_high":888.2,"eq_low":858.35,"eq_close":863.1,"fut_volume":14651,"fut_oi":74178000,"fut_oi_change":1150500,"fut_turnover":9619127437.5,"opt_volume":76234,"opt_oi":40712250,"opt_turnover":52437352650,"ce_volume":42558,"pe_volume":33676},"CANBK":{"eq_volume":21773776,"eq_turnover":3047855669.62,"eq_high":142.86,"eq_low":136.26,"eq_close":140.34,"fut_volume":6804,"fut_oi":170565750,"fut_oi_change":-27000,"fut_turnover":6432958777.5,"opt_volume":20294,"opt_oi":190633500,"opt_turnover":20198045655,"ce_volume":13012,"pe_volume":7282},"DMART":{"eq_volume":352801,"eq_turnover":1387799789.1,"eq_high":3975,"eq_low":3856.2,"eq_close":3953.6,"fut_volume":6172,"fut_oi":5621550,"fut_oi_change":139500,"fut_turnover":3646434510,"opt_volume":19048,"opt_oi":2323200,"opt_turnover":11556273600,"ce_volume":12819,"pe_volume":6229},"IREDA":{"eq_volume":9357674,"eq_turnover":1088518483.62,"eq_high":118.95,"eq_low":112.59,"eq_close":117.03,"fut_volume":2223,"fut_oi":56673150,"fut_oi_change":-203550,"fut_turnover":888386764.5,"opt_volume":5986,"opt_oi":48151650,"opt_turnover":2552448517.5,"ce_volume":4895,"pe_volume":1091},"LICHSGFIN":{"eq_volume":2540980,"eq_turnover":1269459133.9,"eq_high":506.15,"eq_low":492,"eq_close":498.5,"fut_volume":2339,"fut_oi":27774000,"fut_oi_change":639000,"fut_turnover":1173726450,"opt_volume":7634,"opt_oi":13331000,"opt_turnover":3907503550,"ce_volume":4213,"pe_volume":3421},"LTM":{"eq_volume":229386,"eq_turnover":990023374.1,"eq_high":4372.9,"eq_low":4220,"eq_close":4323.6,"fut_volume":2748,"fut_oi":3329100,"fut_oi_change":61800,"fut_turnover":1766579460,"opt_volume":9443,"opt_oi":2262000,"opt_turnover":6390395587.5,"ce_volume":6689,"pe_volume":2754},"LUPIN":{"eq_volume":870863,"eq_turnover":2039161088.1,"eq_high":2361.4,"eq_low":2306,"eq_close":2357.3,"fut_volume":2957,"fut_oi":7259425,"fut_oi_change":174675,"fut_turnover":2944435190,"opt_volume":15666,"opt_oi":5745150,"opt_turnover":16020754907.5,"ce_volume":10269,"pe_volume":5397},"SHRIRAMFIN":{"eq_volume":7054662,"eq_turnover":7245450325.6,"eq_high":1046.7,"eq_low":1006.1,"eq_close":1031.7,"fut_volume":9506,"fut_oi":38416950,"fut_oi_change":405900,"fut_turnover":8078186820,"opt_volume":41183,"opt_oi":23151975,"opt_turnover":36233339628.75,"ce_volume":24550,"pe_volume":16633},"TMPV":{"eq_volume":9707654,"eq_turnover":3168644990.8,"eq_high":333,"eq_low":323.35,"eq_close":324.55,"fut_volume":14137,"fut_oi":66020800,"fut_oi_change":-875200,"fut_turnover":3698504080,"opt_volume":86618,"opt_oi":79380000,"opt_turnover":23934572400,"ce_volume":51014,"pe_volume":35604},"HINDZINC":{"eq_volume":4378868,"eq_turnover":2528393362.8,"eq_high":585.65,"eq_low":568.85,"eq_close":583,"fut_volume":3992,"fut_oi":33306525,"fut_oi_change":-109025,"fut_turnover":2829315798.75,"opt_volume":24305,"opt_oi":43265775,"opt_turnover":18201331321.25,"ce_volume":15479,"pe_volume":8826},"RVNL":{"eq_volume":6945305,"eq_turnover":1930505552.15,"eq_high":284.35,"eq_low":270.95,"eq_close":279.6,"fut_volume":4323,"fut_oi":52707050,"fut_oi_change":-1604300,"fut_turnover":1829907203.75,"opt_volume":21603,"opt_oi":48249475,"opt_turnover":9858471613.75,"ce_volume":15515,"pe_volume":6088},"ANGELONE":{"eq_volume":10674079,"eq_turnover":2289601727.6,"eq_high":217.5,"eq_low":212.36,"eq_close":213.07,"fut_volume":3905,"fut_oi":32077500,"fut_oi_change":702500,"fut_turnover":2100091100,"opt_volume":9419,"opt_oi":40890000,"opt_turnover":5394502400,"ce_volume":6060,"pe_volume":3359},"AUBANK":{"eq_volume":1828277,"eq_turnover":1655273121.25,"eq_high":912.75,"eq_low":899.1,"eq_close":902.2,"fut_volume":3865,"fut_oi":24224000,"fut_oi_change":477000,"fut_turnover":3512046350,"opt_volume":14633,"opt_oi":15368000,"opt_turnover":13831233600,"ce_volume":8406,"pe_volume":6227},"BANDHANBNK":{"eq_volume":5408689,"eq_turnover":967538015.64,"eq_high":181.47,"eq_low":177.2,"eq_close":178.01,"fut_volume":3811,"fut_oi":93650400,"fut_oi_change":1641600,"fut_turnover":2463203232,"opt_volume":7614,"opt_oi":55609200,"opt_turnover":5135951700,"ce_volume":4873,"pe_volume":2741},"CAMS":{"eq_volume":1585361,"eq_turnover":1050212288.05,"eq_high":670.8,"eq_low":655.25,"eq_close":663.75,"fut_volume":2047,"fut_oi":6041250,"fut_oi_change":-279750,"fut_turnover":1018434750,"opt_volume":4865,"opt_oi":6546000,"opt_turnover":2508966787.5,"ce_volume":2742,"pe_volume":2123},"HINDALCO":{"eq_volume":4664967,"eq_turnover":4455577847.1,"eq_high":972,"eq_low":934.45,"eq_close":969.75,"fut_volume":11173,"fut_oi":37509500,"fut_oi_change":279300,"fut_turnover":7486221260,"opt_volume":47106,"opt_oi":20112400,"opt_turnover":32345032230,"ce_volume":28699,"pe_volume":18407},"IRFC":{"eq_volume":14255322,"eq_turnover":1416965106.23,"eq_high":100.9,"eq_low":97.25,"eq_close":99.92,"fut_volume":2528,"fut_oi":60830250,"fut_oi_change":-1513000,"fut_turnover":1056565555,"opt_volume":13918,"opt_oi":130058500,"opt_turnover":6134654000,"ce_volume":10419,"pe_volume":3499},"NAUKRI":{"eq_volume":2942812,"eq_turnover":2782533299.7,"eq_high":957.1,"eq_low":937.9,"eq_close":955.4,"fut_volume":2646,"fut_oi":10881375,"fut_oi_change":52875,"fut_turnover":943479487.5,"opt_volume":10680,"opt_oi":5710125,"opt_turnover":4043797293.75,"ce_volume":7823,"pe_volume":2857},"RECLTD":{"eq_volume":10658407,"eq_turnover":3627429347.85,"eq_high":349.45,"eq_low":327.3,"eq_close":343.5,"fut_volume":9788,"fut_oi":70474600,"fut_oi_change":-886200,"fut_turnover":4635896510,"opt_volume":47629,"opt_oi":60740400,"opt_turnover":23602915840,"ce_volume":33192,"pe_volume":14437},"SBICARD":{"eq_volume":831279,"eq_turnover":588045197.3,"eq_high":715,"eq_low":698,"eq_close":710.25,"fut_volume":3021,"fut_oi":22792000,"fut_oi_change":311200,"fut_turnover":1664690080,"opt_volume":5859,"opt_oi":13424800,"opt_turnover":3456002360,"ce_volume":4005,"pe_volume":1854},"TORNTPHARM":{"eq_volume":322856,"eq_turnover":1429472039.7,"eq_high":4460.2,"eq_low":4391,"eq_close":4446,"fut_volume":1464,"fut_oi":2696500,"fut_oi_change":-20000,"fut_turnover":1622316450,"opt_volume":4888,"opt_oi":1514500,"opt_turnover":5555454650,"ce_volume":3568,"pe_volume":1320},"VBL":{"eq_volume":12325188,"eq_turnover":5118012878,"eq_high":432,"eq_low":410,"eq_close":411.05,"fut_volume":9741,"fut_oi":40417875,"fut_oi_change":40500,"fut_turnover":4562227068.75,"opt_volume":33246,"opt_oi":24511500,"opt_turnover":16322164593.75,"ce_volume":19356,"pe_volume":13890},"WAAREEENER":{"eq_volume":1330806,"eq_turnover":3589142507.2,"eq_high":2759.6,"eq_low":2615,"eq_close":2739.4,"fut_volume":5722,"fut_oi":3408125,"fut_oi_change":-61425,"fut_turnover":2721851107.5,"opt_volume":28299,"opt_oi":4386900,"opt_turnover":13999204765,"ce_volume":19592,"pe_volume":8707},"TATATECH":{"eq_volume":822824,"eq_turnover":453809700.65,"eq_high":559.4,"eq_low":544.45,"eq_close":551.85,"fut_volume":1199,"fut_oi":10111200,"fut_oi_change":-180000,"fut_turnover":530474400,"opt_volume":3641,"opt_oi":7120000,"opt_turnover":1730506280,"ce_volume":2751,"pe_volume":890}}}